aspose/__init__.py
aspose/asposeocr.py
aspose/helper.py
aspose/license.py
aspose/models.py
aspose/recognitionresult.py
aspose/recognitionsettings.py
aspose/jlib/__init__.py
aspose/jlib/aspose-ocr-24.7.0.jar
aspose/jlib/aspose-pdf-24.2.jar
aspose/jlib/onnxruntime-1.16.0.jar
aspose_ocr_python_java-24.7.0.dist-info/LICENSE
aspose_ocr_python_java-24.7.0.dist-info/METADATA
aspose_ocr_python_java-24.7.0.dist-info/WHEEL
aspose_ocr_python_java-24.7.0.dist-info/top_level.txt
aspose_ocr_python_java-24.7.0.dist-info/RECORD
