Metadata-Version: 2.1
Name: aspose-ocr-python-java
Version: 24.7.0
Summary: Aspose.OCR for Python via .Java is a powerful, while easy-to-use optical character recognition (OCR) engine for your Python applications and notebooks.
Home-page: https://products.aspose.com/ocr/
Author: Aspose
Author-email: aleksander.golshtain@aspose.com
Project-URL: GitHub, https://github.com/aspose-ocr/Aspose.OCR-for-Python-via-Java
Keywords: aspose,ocr,java
Classifier: Programming Language :: Python :: 3.8
Classifier: License :: Other/Proprietary License
Requires-Python: >=3.8
License-File: LICENSE
Requires-Dist: JPype1 (==1.4.1)
